odoo/addons/cooperator_website_referral_source/README.rst
odoo/addons/cooperator_website_referral_source/__init__.py
odoo/addons/cooperator_website_referral_source/__manifest__.py
odoo/addons/cooperator_website_referral_source/controllers/__init__.py
odoo/addons/cooperator_website_referral_source/controllers/main.py
odoo/addons/cooperator_website_referral_source/i18n/cooperator_website_referral_source.pot
odoo/addons/cooperator_website_referral_source/i18n/it.po
odoo/addons/cooperator_website_referral_source/models/__init__.py
odoo/addons/cooperator_website_referral_source/models/referral_source.py
odoo/addons/cooperator_website_referral_source/models/res_partner.py
odoo/addons/cooperator_website_referral_source/models/subscription_request.py
odoo/addons/cooperator_website_referral_source/readme/CONTRIBUTORS.rst
odoo/addons/cooperator_website_referral_source/readme/DESCRIPTION.rst
odoo/addons/cooperator_website_referral_source/security/ir.model.access.csv
odoo/addons/cooperator_website_referral_source/static/description/icon.png
odoo/addons/cooperator_website_referral_source/static/description/index.html
odoo/addons/cooperator_website_referral_source/views/referral_source_view.xml
odoo/addons/cooperator_website_referral_source/views/res_partner_view.xml
odoo/addons/cooperator_website_referral_source/views/subscription_request_view.xml
odoo/addons/cooperator_website_referral_source/views/subscription_template.xml
odoo12_addon_cooperator_website_referral_source-12.0.1.0.0.99.dev8.dist-info/METADATA
odoo12_addon_cooperator_website_referral_source-12.0.1.0.0.99.dev8.dist-info/WHEEL
odoo12_addon_cooperator_website_referral_source-12.0.1.0.0.99.dev8.dist-info/top_level.txt
odoo12_addon_cooperator_website_referral_source-12.0.1.0.0.99.dev8.dist-info/RECORD
