Metadata-Version: 2.1
Name: odoo12-addon-cooperator_website_referral_source
Version: 12.0.1.0.0.99.dev8
Summary: Add a Selection field in the form to select how the respondent discovered the cooperative.
Home-page: https://github.com/OCA/cooperative
Author: Coop IT Easy SC, Odoo Community Association (OCA)
Author-email: support@odoo-community.org
License: AGPL-3
Classifier: Programming Language :: Python
Classifier: Framework :: Odoo
Classifier: Framework :: Odoo :: 12.0
Classifier: License :: OSI Approved :: GNU Affero General Public License v3
Requires-Python: >=3.5
Requires-Dist: odoo12-addon-cooperator-website
Requires-Dist: odoo<12.1dev,>=12.0a
